datasette_plugin_demos/__init__.py
datasette_plugin_demos/static/plugin.js
datasette_plugin_demos/templates/show_json.html
datasette_plugin_demos-0.4.dist-info/METADATA
datasette_plugin_demos-0.4.dist-info/WHEEL
datasette_plugin_demos-0.4.dist-info/entry_points.txt
datasette_plugin_demos-0.4.dist-info/top_level.txt
datasette_plugin_demos-0.4.dist-info/RECORD
