Metadata-Version: 2.1
Name: datasette-plugin-demos
Version: 0.4
Summary: Examples of plugins for Datasette
Home-page: https://github.com/simonw/datasette-plugin-demos
Author: Simon Willison
License: Apache License, Version 2.0
Platform: UNKNOWN
Requires-Dist: datasette
Provides-Extra: test
Requires-Dist: pytest ; extra == 'test'
Requires-Dist: pytest-asyncio ; extra == 'test'
Requires-Dist: httpx ; extra == 'test'
